#ifndef OPCODE_H
#define OPCODE_H

class Opcode {
public:
    static constexpr uint8_t NOP             = 0x00;
    static constexpr uint8_t ACONST_NULL     = 0x01;
    static constexpr uint8_t ICONST_M1       = 0x02;
    static constexpr uint8_t ICONST_0        = 0x03;
    static constexpr uint8_t ICONST_1        = 0x04;
    static constexpr uint8_t ICONST_2        = 0x05;
    static constexpr uint8_t ICONST_3        = 0x06;
    static constexpr uint8_t ICONST_4        = 0x07;
    static constexpr uint8_t ICONST_5        = 0x08;
    static constexpr uint8_t LCONST_0        = 0x09;
    static constexpr uint8_t LCONST_1        = 0x0a;
    static constexpr uint8_t FCONST_0        = 0x0b;
    static constexpr uint8_t FCONST_1        = 0x0c;
    static constexpr uint8_t FCONST_2        = 0x0d;
    static constexpr uint8_t DCONST_0        = 0x0e;
    static constexpr uint8_t DCONST_1        = 0x0f;
    static constexpr uint8_t BIPUSH          = 0x10;
    static constexpr uint8_t SIPUSH          = 0x11;
    static constexpr uint8_t LDC             = 0x12;
    static constexpr uint8_t LDC_W           = 0x13;
    static constexpr uint8_t LDC2_W          = 0x14;
    static constexpr uint8_t ILOAD           = 0x15;
    static constexpr uint8_t LLOAD           = 0x16;
    static constexpr uint8_t FLOAD           = 0x17;
    static constexpr uint8_t DLOAD           = 0x18;
    static constexpr uint8_t ALOAD           = 0x19;
    static constexpr uint8_t ILOAD_0         = 0x1a;
    static constexpr uint8_t ILOAD_1         = 0x1b;
    static constexpr uint8_t ILOAD_2         = 0x1c;
    static constexpr uint8_t ILOAD_3         = 0x1d;
    static constexpr uint8_t LLOAD_0         = 0x1e;
    static constexpr uint8_t LLOAD_1         = 0x1f;
    static constexpr uint8_t LLOAD_2         = 0x20;
    static constexpr uint8_t LLOAD_3         = 0x21;
    static constexpr uint8_t FLOAD_0         = 0x22;
    static constexpr uint8_t FLOAD_1         = 0x23;
    static constexpr uint8_t FLOAD_2         = 0x24;
    static constexpr uint8_t FLOAD_3         = 0x25;
    static constexpr uint8_t DLOAD_0         = 0x26;
    static constexpr uint8_t DLOAD_1         = 0x27;
    static constexpr uint8_t DLOAD_2         = 0x28;
    static constexpr uint8_t DLOAD_3         = 0x29;
    static constexpr uint8_t ALOAD_0         = 0x2a;
    static constexpr uint8_t ALOAD_1         = 0x2b;
    static constexpr uint8_t ALOAD_2         = 0x2c;
    static constexpr uint8_t ALOAD_3         = 0x2d;
    static constexpr uint8_t IALOAD          = 0x2e;
    static constexpr uint8_t LALOAD          = 0x2f;
    static constexpr uint8_t FALOAD          = 0x30;
    static constexpr uint8_t DALOAD          = 0x31;
    static constexpr uint8_t AALOAD          = 0x32;
    static constexpr uint8_t BALOAD          = 0x33;
    static constexpr uint8_t CALOAD          = 0x34;
    static constexpr uint8_t SALOAD          = 0x35;
    static constexpr uint8_t ISTORE          = 0x36;
    static constexpr uint8_t LSTORE          = 0x37;
    static constexpr uint8_t FSTORE          = 0x38;
    static constexpr uint8_t DSTORE          = 0x39;
    static constexpr uint8_t ASTORE          = 0x3a;
    static constexpr uint8_t ISTORE_0        = 0x3b;
    static constexpr uint8_t ISTORE_1        = 0x3c;
    static constexpr uint8_t ISTORE_2        = 0x3d;
    static constexpr uint8_t ISTORE_3        = 0x3e;
    static constexpr uint8_t LSTORE_0        = 0x3f;
    static constexpr uint8_t LSTORE_1        = 0x40;
    static constexpr uint8_t LSTORE_2        = 0x41;
    static constexpr uint8_t LSTORE_3        = 0x42;
    static constexpr uint8_t FSTORE_0        = 0x43;
    static constexpr uint8_t FSTORE_1        = 0x44;
    static constexpr uint8_t FSTORE_2        = 0x45;
    static constexpr uint8_t FSTORE_3        = 0x46;
    static constexpr uint8_t DSTORE_0        = 0x47;
    static constexpr uint8_t DSTORE_1        = 0x48;
    static constexpr uint8_t DSTORE_2        = 0x49;
    static constexpr uint8_t DSTORE_3        = 0x4a;
    static constexpr uint8_t ASTORE_0        = 0x4b;
    static constexpr uint8_t ASTORE_1        = 0x4c;
    static constexpr uint8_t ASTORE_2        = 0x4d;
    static constexpr uint8_t ASTORE_3        = 0x4e;
    static constexpr uint8_t IASTORE         = 0x4f;
    static constexpr uint8_t LASTORE         = 0x50;
    static constexpr uint8_t FASTORE         = 0x51;
    static constexpr uint8_t DASTORE         = 0x52;
    static constexpr uint8_t AASTORE         = 0x53;
    static constexpr uint8_t BASTORE         = 0x54;
    static constexpr uint8_t CASTORE         = 0x55;
    static constexpr uint8_t SASTORE         = 0x56;
    static constexpr uint8_t POP             = 0x57;
    static constexpr uint8_t POP2            = 0x58;
    static constexpr uint8_t DUP             = 0x59;
    static constexpr uint8_t DUP_X1          = 0x5a;
    static constexpr uint8_t DUP_X2          = 0x5b;
    static constexpr uint8_t DUP2            = 0x5c;
    static constexpr uint8_t DUP2_X1         = 0x5d;
    static constexpr uint8_t DUP2_X2         = 0x5e;
    static constexpr uint8_t SWAP            = 0x5f;
    static constexpr uint8_t IADD            = 0x60;
    static constexpr uint8_t LADD            = 0x61;
    static constexpr uint8_t FADD            = 0x62;
    static constexpr uint8_t DADD            = 0x63;
    static constexpr uint8_t ISUB            = 0x64;
    static constexpr uint8_t LSUB            = 0x65;
    static constexpr uint8_t FSUB            = 0x66;
    static constexpr uint8_t DSUB            = 0x67;
    static constexpr uint8_t IMUL            = 0x68;
    static constexpr uint8_t LMUL            = 0x69;
    static constexpr uint8_t FMUL            = 0x6a;
    static constexpr uint8_t DMUL            = 0x6b;
    static constexpr uint8_t IDIV            = 0x6c;
    static constexpr uint8_t LDIV            = 0x6d;
    static constexpr uint8_t FDIV            = 0x6e;
    static constexpr uint8_t DDIV            = 0x6f;
    static constexpr uint8_t IREM            = 0x70;
    static constexpr uint8_t LREM            = 0x71;
    static constexpr uint8_t FREM            = 0x72;
    static constexpr uint8_t DREM            = 0x73;
    static constexpr uint8_t INEG            = 0x74;
    static constexpr uint8_t LNEG            = 0x75;
    static constexpr uint8_t FNEG            = 0x76;
    static constexpr uint8_t DNEG            = 0x77;
    static constexpr uint8_t ISHL            = 0x78;
    static constexpr uint8_t LSHL            = 0x79;
    static constexpr uint8_t ISHR            = 0x7a;
    static constexpr uint8_t LSHR            = 0x7b;
    static constexpr uint8_t IUSHR           = 0x7c;
    static constexpr uint8_t LUSHR           = 0x7d;
    static constexpr uint8_t IAND            = 0x7e;
    static constexpr uint8_t LAND            = 0x7f;
    static constexpr uint8_t IOR             = 0x80;
    static constexpr uint8_t LOR             = 0x81;
    static constexpr uint8_t IXOR            = 0x82;
    static constexpr uint8_t LXOR            = 0x83;
    static constexpr uint8_t IINC            = 0x84;
    static constexpr uint8_t I2L             = 0x85;
    static constexpr uint8_t I2F             = 0x86;
    static constexpr uint8_t I2D             = 0x87;
    static constexpr uint8_t L2I             = 0x88;
    static constexpr uint8_t L2F             = 0x89;
    static constexpr uint8_t L2D             = 0x8a;
    static constexpr uint8_t F2I             = 0x8b;
    static constexpr uint8_t F2L             = 0x8c;
    static constexpr uint8_t F2D             = 0x8d;
    static constexpr uint8_t D2I             = 0x8e;
    static constexpr uint8_t D2L             = 0x8f;
    static constexpr uint8_t D2F             = 0x90;
    static constexpr uint8_t I2B             = 0x91;
    static constexpr uint8_t I2C             = 0x92;
    static constexpr uint8_t I2S             = 0x93;
    static constexpr uint8_t LCMP            = 0x94;
    static constexpr uint8_t FCMPL           = 0x95;
    static constexpr uint8_t FCMPG           = 0x96;
    static constexpr uint8_t DCMPL           = 0x97;
    static constexpr uint8_t DCMPG           = 0x98;
    static constexpr uint8_t IFEQ            = 0x99;
    static constexpr uint8_t IFNE            = 0x9a;
    static constexpr uint8_t IFLT            = 0x9b;
    static constexpr uint8_t IFGE            = 0x9c;
    static constexpr uint8_t IFGT            = 0x9d;
    static constexpr uint8_t IFLE            = 0x9e;
    static constexpr uint8_t IF_ICMPEQ       = 0x9f;
    static constexpr uint8_t IF_ICMPNE       = 0xa0;
    static constexpr uint8_t IF_ICMPLT       = 0xa1;
    static constexpr uint8_t IF_ICMPGE       = 0xa2;
    static constexpr uint8_t IF_ICMPGT       = 0xa3;
    static constexpr uint8_t IF_ICMPLE       = 0xa4;
    static constexpr uint8_t IF_ACMPEQ       = 0xa5;
    static constexpr uint8_t IF_ACMPNE       = 0xa6;
    static constexpr uint8_t GOTO            = 0xa7;
    static constexpr uint8_t JSR             = 0xa8;
    static constexpr uint8_t RET             = 0xa9;
    static constexpr uint8_t TABLESWITCH     = 0xaa;
    static constexpr uint8_t LOOKUPSWITCH    = 0xab;
    static constexpr uint8_t IRETURN         = 0xac;
    static constexpr uint8_t LRETURN         = 0xad;
    static constexpr uint8_t FRETURN         = 0xae;
    static constexpr uint8_t DRETURN         = 0xaf;
    static constexpr uint8_t ARETURN         = 0xb0;
    static constexpr uint8_t RETURN          = 0xb1;
    static constexpr uint8_t GETSTATIC       = 0xb2;
    static constexpr uint8_t PUTSTATIC       = 0xb3;
    static constexpr uint8_t GETFIELD        = 0xb4;
    static constexpr uint8_t PUTFIELD        = 0xb5;
    static constexpr uint8_t INVOKEVIRTUAL   = 0xb6;
    static constexpr uint8_t INVOKESPECIAL   = 0xb7;
    static constexpr uint8_t INVOKESTATIC    = 0xb8;
    static constexpr uint8_t INVOKEINTERFACE = 0xb9;
    static constexpr uint8_t INVOKEDYNAMIC   = 0xba;
    static constexpr uint8_t NEW             = 0xbb;
    static constexpr uint8_t NEWARRAY        = 0xbc;
    static constexpr uint8_t ANEWARRAY       = 0xbd;
    static constexpr uint8_t ARRAYLENGTH     = 0xbe;
    static constexpr uint8_t ATHROW          = 0xbf;
    static constexpr uint8_t CHECKCAST       = 0xc0;
    static constexpr uint8_t INSTANCEOF      = 0xc1;
    static constexpr uint8_t MONITORENTER    = 0xc2;
    static constexpr uint8_t MONITOREXIT     = 0xc3;
    static constexpr uint8_t WIDE            = 0xc4;
    static constexpr uint8_t MULTIANEWARRAY  = 0xc5;
    static constexpr uint8_t IFNULL          = 0xc6;
    static constexpr uint8_t IFNONNULL       = 0xc7;
    static constexpr uint8_t GOTO_W          = 0xc8;
    static constexpr uint8_t JSR_W           = 0xc9;
    static constexpr uint8_t BREAKPOINT      = 0xca;
    static constexpr uint8_t IMPDEP1         = 0xfe;
    static constexpr uint8_t IMPDEP2         = 0xff;
};

#endif
